setup.py
django_multiple_domain.egg-info/PKG-INFO
django_multiple_domain.egg-info/SOURCES.txt
django_multiple_domain.egg-info/dependency_links.txt
django_multiple_domain.egg-info/requires.txt
django_multiple_domain.egg-info/top_level.txt
multidomain/__init__.py
multidomain/admin.py
multidomain/apps.py
multidomain/http.py
multidomain/middleware.py
multidomain/models.py
multidomain/tests.py